kalista/__init__.py
kalista/helpers.py
kalista/models/__init__.py
kalista/models/exceptions.py
kalista/models/game.py
kalista/models/league.py
kalista/models/match.py
kalista/models/player.py
kalista/models/schedule.py
kalista/models/standings.py
kalista/models/team.py
kalista/models/tournament.py
kalista-0.1.12.dist-info/LICENSE
kalista-0.1.12.dist-info/METADATA
kalista-0.1.12.dist-info/WHEEL
kalista-0.1.12.dist-info/RECORD
